{"stats":{"minecraft:killed":{"twilightforest:boar":1,"minecraft:pig":1,"twilightforest:kobold":1,"minecraft:sheep":1,"minecraft:skeleton":1,"minecraft:zombie":1,"minecraft:chicken":1,"twilightforest:bighorn_sheep":2},"minecraft:picked_up":{"minecraft:cocoa_beans":3,"minecraft:crafting_table":4,"minecraft:wheat":2,"minecraft:feather":2,"twilightforest:twilight_oak_log":5,"minecraft:chicken":1,"minecraft:brown_wool":1,"minecraft:brown_mushroom":18,"minecraft:red_mushroom":12,"minecraft:oak_log":28,"minecraft:dirt":63,"minecraft:smooth_stone_slab":2,"minecraft:bone":1,"minecraft:blue_orchid":1,"minecraft:apple":1,"minecraft:wheat_seeds":4,"minecraft:cooked_chicken":1,"minecraft:rose_bush":1,"minecraft:written_book":1,"minecraft:light_gray_wool":1,"minecraft:oak_planks":1,"minecraft:egg":2,"minecraft:furnace":3,"twilightforest:mushgloom":9,"minecraft:stick":8,"minecraft:pumpkin":1,"minecraft:bowl":2,"minecraft:porkchop":3,"twilightforest:canopy_log":3,"tombstone:grave_dust":2,"minecraft:arrow":2,"twilightforest:twilight_oak_sapling":2,"minecraft:oak_sapling":12,"minecraft:mutton":5,"minecraft:white_wool":1,"minecraft:cobblestone":18},"minecraft:crafted":{"minecraft:oak_planks":24,"minecraft:cooked_porkchop":3,"minecraft:crafting_table":1,"minecraft:wooden_pickaxe":1,"minecraft:bowl":4,"minecraft:furnace":1,"minecraft:mushroom_stew":8,"minecraft:stone_axe":1,"minecraft:cooked_mutton":5,"minecraft:air":0,"minecraft:stick":4,"minecraft:stone_pickaxe":1,"minecraft:wooden_axe":1,"minecraft:stone_sword":1},"minecraft:used":{"minecraft:cooked_mutton":3,"minecraft:rose_bush":1,"minecraft:stone_sword":79,"minecraft:stone_pickaxe":2,"minecraft:wooden_pickaxe":45,"minecraft:cooked_chicken":1,"minecraft:dirt":63,"minecraft:crafting_table":4,"minecraft:mushroom_stew":3,"minecraft:wooden_axe":23,"minecraft:blue_orchid":1,"minecraft:stone_axe":131,"minecraft:written_book":1,"minecraft:furnace":3,"minecraft:cooked_porkchop":1,"minecraft:egg":2},"minecraft:killed_by":{"minecraft:zombie":1},"minecraft:dropped":{"minecraft:wheat":2,"minecraft:feather":2,"twilightforest:twilight_oak_sapling":2,"minecraft:mushroom_stew":1,"minecraft:oak_sapling":12,"tombstone:grave_dust":1},"minecraft:mined":{"minecraft:brown_mushroom":2,"minecraft:crafting_table":4,"minecraft:grass_block":26,"twilightforest:twilight_oak_log":5,"minecraft:mushroom_stem":12,"minecraft:brown_mushroom_block":36,"twilightforest:mushgloom":9,"minecraft:furnace":3,"twilightforest:twilight_oak_leaves":2,"minecraft:pumpkin":1,"minecraft:grass":42,"minecraft:oak_log":29,"minecraft:cocoa":1,"minecraft:dirt":37,"minecraft:stone":18,"minecraft:red_mushroom_block":55,"minecraft:blue_orchid":1,"twilightforest:canopy_log":3,"minecraft:oak_leaves":3},"minecraft:custom":{"minecraft:interact_with_furnace":11,"minecraft:mob_kills":9,"minecraft:interact_with_crafting_table":11,"minecraft:time_since_death":4543,"minecraft:climb_one_cm":124,"minecraft:time_since_rest":3619,"minecraft:sprint_one_cm":27443,"minecraft:damage_taken":852,"minecraft:walk_one_cm":328086,"minecraft:drop":18,"minecraft:damage_dealt":917,"minecraft:swim_one_cm":7380,"minecraft:fly_one_cm":186426,"minecraft:open_chest":3,"minecraft:play_time":42585,"tombstone:undead_killed":2,"minecraft:deaths":1,"minecraft:walk_under_water_one_cm":2006,"minecraft:jump":291,"minecraft:walk_on_water_one_cm":5257,"minecraft:total_world_time":42585,"minecraft:fall_one_cm":5623}},"DataVersion":3465}